{
  "time":"2020-05-13 21:00:05",
  "title":"抽屉新热榜",
  "data":[
    {
      "name":"潘乱：所有人，所有内容，都成为系统服务的燃料",
      "url":"https://36kr.com/p/705665712880774"
    },
    {
      "name":"【“预言”了2020肺炎的女灵媒，靠谱度究竟几何？】由于关于2020年传染病的前半部分与事实惊人地吻合，一些人居然相信这位7年前过世的女灵媒真有预言未来的本领。其实，她所作的大部分预言都没有被证实，比如她说特朗普在政治上不会取得任何成功。",
      "url":"https://mp.weixin.qq.com/s/RrjSeOdQNfPAvXXNbWDw3g"
    },
    {
      "name":"【快递小哥们】“你干什么的？为什么打人？”下面那个人喊：“快帮我报警呀！我好好的取快递，这个疯子冲上来就打我。你看把我眼镜也打碎了，东西也打烂了！”打人的小伙子举着几个小瓶子说：“我怀疑他贩毒、偷电动车，还有撬快递柜。”",
      "url":"https://www.douban.com/note/761676806/"
    },
    {
      "name":"威士忌从入门到买房：你说的桶，它好喝吗",
      "url":"https://www.gcores.com/articles/123692"
    },
    {
      "name":"5月11日，吉尼斯世界纪录介绍了新认证的最年长游戏玩家森滨子。森滨子来自日本千叶县，今年已年满90岁。她与游戏的缘分可以追溯至1981年，家中还存有大量游戏卡带。老太太称，自己如今每天花7、8个小时打游戏。",
      "url":"http://n.miaopai.com/media/PCbwmOO10IW0seRjuiqQEQ7HvbY3hr-5"
    },
    {
      "name":"土豪方便面，刀削牛肉泡面",
      "url":"https://www.bilibili.com/video/BV1ap4y1Q7WH"
    },
    {
      "name":"【鹅组回归八组本质，八一下PAPI热搜这几天下场各方的时间线】 说法一称极端女权把PAPI酱骂上了热搜，说法二是PAPI酱自己买热搜炒作，说法三是有人要借机污名女权分化女性。这么多的说法让我想起了一个游戏————剧本杀，就照剧本杀的玩法开帖来捋一下这次冠姓权的时间线。",
      "url":"https://www.douban.com/group/topic/175337218/"
    },
    {
      "name":"【武汉大学毕业班疫情实录】梁贻也想再看看，如果欧洲疫情控制得不理想，她可能会留在国内，先做些和德语有关的兼职，然后再申请明年春季入学。父母是同样的想法，劝她今年先留在国内。",
      "url":"https://www.toutiao.com/i6825927436539003406/"
    },
    {
      "name":"物理学家发现自然常数在变化，宇宙或不具有“各向同性”",
      "url":"https://mp.weixin.qq.com/s?__biz=MzA3NTIyODUzNA==&mid=2649587320&idx=5&sn=31a91ee50afc15df801ef641de221a10&chksm=876a6a61b01de37735a7500f282cd0a58c58693ffbbc06493718fbcb61d3406b7b33ddf9b8a6&token=527659867&lang=zh_CN#rd"
    },
    {
      "name":"【多帅才能当直女斩？】无论是男生女生，大家都更关注「直男斩」和相关分析，但反过来，好像大家对讨论男性「直女斩」「万人迷」的热情就没有那么高。当代女生对于男性的审美到底如何？我们真的喜欢更「娘」的男生吗？",
      "url":"https://mp.weixin.qq.com/s/J0w24vGAeV0c9SNFYTe_pA"
    },
    {
      "name":"【“老挝”读音之谜  我在明朝古书找到了答案】我们是因为误读，把“老挝”读成了现在的“老窝”，本来应该读“老抓”。而“老挝”这个名字能流传至今以及当时对应的外文原文，离不开我国最早的官方翻译机构明朝四夷馆人员的专业。",
      "url":"https://mp.weixin.qq.com/s/GxrIRlXhepu2G8y0igyCow"
    },
    {
      "name":"北京春天的常见花，北方通用",
      "url":"https://video.weibo.com/show?fid=1034:4504152743542819"
    },
    {
      "name":"狗子：没啥，我就动一下风扇罢了，你当作没看见哈",
      "url":"https://video.weibo.com/show?fid=1034:4501903531245573"
    },
    {
      "name":"腾讯控股第一季度业绩超市场预期",
      "url":"https://www.laohu8.com/news/1134528797"
    },
    {
      "name":"【《午夜福音》：ADD重症患者良药】Netfilx成人向动画作品，主人公克兰西利用多宇宙模拟器探访其他宇宙生物的生活，经营自己的播客。他独居，住在拖车里，善于逃避，每次星球冒险都如同一次重生。他聆听奇形怪状的采访对象的冥想与死亡观，亲自体验他们漫长的死亡过程。每期可爱至极的画风和密度过大的对话，都很迷幻。",
      "url":"https://www.thepaper.cn/newsDetail_forward_7120750"
    },
    {
      "name":"规范法语正统性的权威机构法兰西学院认定，“Covid-19”这个词定为阴性。Covid是英文单词 \"Coronavirus disease \"的缩写，译为 \"冠状病毒病\"。 由于冠状病毒是一种病， \"病 \"在法语里是一个阴性词，所以在使用Covid这个词的时候，规则应该是使用阴性。",
      "url":"https://mp.weixin.qq.com/s/U58Ai-mYfrddVzTPc6XSYQ"
    },
    {
      "name":"核武狂魔黄仁勋从烤箱中端出了“世界上最大、最重的显卡” DGX A100，并表示“它已经预热了一段时间了”。外媒称这款搭载8个Tesla A100 GPU的系统将会在GTC 2020大会上展示。目前的爆料信息显示，Tesla A100 采用了安培架构核心，这也是第一款安培架构的产品。",
      "url":"https://video.weibo.com/show?fid=1034:4504074888871979"
    },
    {
      "name":"美国财政部公布的月度预算报告显示，4月份财政赤字高达7380亿美元，创有史以来最高单月赤字记录。而今年迄今，累积财政赤字已经达到1.48万亿美元，是去年同期的近3倍。对财政部来说，4月份通常是一个财政盈余月份，因为所得税缴税期的到来。去年同期，美国4月财政盈余为1603亿美元。",
      "url":"https://wisburg.com/viewpoint/729946"
    },
    {
      "name":"从6月6日起，北京的高校具备校园疫情防控条件的，可安排毕业年级学生自愿返校，其他年级具体复课时间由学校结合工作实际自定。全市普通中学高一、高二年级，初一、初二年级和小学六年级，将于2020年6月1日返校上课。小学四年级、五年级于6月8日返校上课，一至三年级同步做好返校准备。",
      "url":"http://m.news.cctv.com/2020/05/13/ARTIr6QRxxlgCZ8qHU82wNVa200513.shtml"
    },
    {
      "name":"韩国警方13日公开N号房创建人“godgod”个人信息，此人名叫文亨旭（音译），1996年生，今年24岁。初中就读于京畿道始兴的论谷中学，高中就读于银杏高中，是韩京大学建筑学部14级的学生，目前是否在读未知。​",
      "url":"https://www.ali213.net/news/html/2020-5/509749.html"
    },
    {
      "name":"【微信又“地震式”改版，这次我们该如何「自救」？】在观察+研究了 n 天之后，我发现了乱序阅读的几个小细节。第一，时间顺序优先的公众号并不全是我常读或星标的，有的甚至我几乎没读过（为了不错过选题才关注的）。第二，越少看公众号的用户，内容的时间顺序越乱。",
      "url":"https://mp.weixin.qq.com/s/QIFaLh-OC_Cdf0Tpt1WSgw"
    },
    {
      "name":"在Quibi看了个神奇的家装节目：《凶宅改造》。设计师应客户要求，对客户买的凶宅（发生过凶杀案的房子）进行改造。让房子现有的主人与凶杀地和谐共处，非常恶趣味。",
      "url":"https://weibo.com/1768267801/J1CfwAMge"
    }
  ]
}