{
  "time":"2020-07-01 15:59:21",
  "title":"全球主机交流论坛",
  "data":[
    {
      "name":"OVH续费价格官方Tk回复，所有讨论结束，续费永久17.88传家",
      "url":"https://www.hostloc.com/forum.php?mod=viewthread&tid=710465&extra=page%3D1%26filter%3Dauthor%26orderby%3Ddateline"
    },
    {
      "name":"收汕头/广州移动nat 麻烦老板pm",
      "url":"https://www.hostloc.com/forum.php?mod=viewthread&tid=710464&extra=page%3D1%26filter%3Dauthor%26orderby%3Ddateline"
    },
    {
      "name":"海南免税新政首日：顶配苹果手机便宜2500元",
      "url":"https://www.hostloc.com/forum.php?mod=viewthread&tid=710460&extra=page%3D1%26filter%3Dauthor%26orderby%3Ddateline"
    },
    {
      "name":"打包出一堆产品!",
      "url":"https://www.hostloc.com/forum.php?mod=viewthread&tid=710459&extra=page%3D1%26filter%3Dauthor%26orderby%3Ddateline"
    },
    {
      "name":"这个dd是失败了吧？",
      "url":"https://www.hostloc.com/forum.php?mod=viewthread&tid=710458&extra=page%3D1%26filter%3Dauthor%26orderby%3Ddateline"
    },
    {
      "name":"来自腾讯的哀怨",
      "url":"https://www.hostloc.com/forum.php?mod=viewthread&tid=710457&extra=page%3D1%26filter%3Dauthor%26orderby%3Ddateline"
    },
    {
      "name":"在与反推技术的斗争中",
      "url":"https://www.hostloc.com/forum.php?mod=viewthread&tid=710456&extra=page%3D1%26filter%3Dauthor%26orderby%3Ddateline"
    },
    {
      "name":"(已拼团成功)，金山云拼团",
      "url":"https://www.hostloc.com/forum.php?mod=viewthread&tid=710453&extra=page%3D1%26filter%3Dauthor%26orderby%3Ddateline"
    },
    {
      "name":"请教下，修改host能直接指向本地IP的端口吗？",
      "url":"https://www.hostloc.com/forum.php?mod=viewthread&tid=710451&extra=page%3D1%26filter%3Dauthor%26orderby%3Ddateline"
    },
    {
      "name":"新车第二年可以自己在京东上买机油自己换吗？",
      "url":"https://www.hostloc.com/forum.php?mod=viewthread&tid=710450&extra=page%3D1%26filter%3Dauthor%26orderby%3Ddateline"
    },
    {
      "name":"收台便宜独服（ks3c/ks7 online 或 ikoula）",
      "url":"https://www.hostloc.com/forum.php?mod=viewthread&tid=710449&extra=page%3D1%26filter%3Dauthor%26orderby%3Ddateline"
    },
    {
      "name":"2020年了买SURFACE PRO 5还值得吗？",
      "url":"https://www.hostloc.com/forum.php?mod=viewthread&tid=710448&extra=page%3D1%26filter%3Dauthor%26orderby%3Ddateline"
    },
    {
      "name":"阿里云抹布测评",
      "url":"https://www.hostloc.com/forum.php?mod=viewthread&tid=710447&extra=page%3D1%26filter%3Dauthor%26orderby%3Ddateline"
    },
    {
      "name":"免费一年的澳大利亚商家网络托管",
      "url":"https://www.hostloc.com/forum.php?mod=viewthread&tid=710446&extra=page%3D1%26filter%3Dauthor%26orderby%3Ddateline"
    },
    {
      "name":"onedrive如何搬运备份到其他网盘",
      "url":"https://www.hostloc.com/forum.php?mod=viewthread&tid=710445&extra=page%3D1%26filter%3Dauthor%26orderby%3Ddateline"
    },
    {
      "name":"有大佬收到12426的邮件吗？",
      "url":"https://www.hostloc.com/forum.php?mod=viewthread&tid=710444&extra=page%3D1%26filter%3Dauthor%26orderby%3Ddateline"
    },
    {
      "name":"gandi码",
      "url":"https://www.hostloc.com/forum.php?mod=viewthread&tid=710443&extra=page%3D1%26filter%3Dauthor%26orderby%3Ddateline"
    },
    {
      "name":"南山法院竟然不能识别伪造章？",
      "url":"https://www.hostloc.com/forum.php?mod=viewthread&tid=710442&extra=page%3D1%26filter%3Dauthor%26orderby%3Ddateline"
    },
    {
      "name":"香港paypal【对不起，无法确认您的身份】",
      "url":"https://www.hostloc.com/forum.php?mod=viewthread&tid=710441&extra=page%3D1%26filter%3Dauthor%26orderby%3Ddateline"
    },
    {
      "name":"为了预防DDCC，可以用套路云反代国外吗",
      "url":"https://www.hostloc.com/forum.php?mod=viewthread&tid=710439&extra=page%3D1%26filter%3Dauthor%26orderby%3Ddateline"
    },
    {
      "name":"终于好了。N3450双网卡+AP！！！",
      "url":"https://www.hostloc.com/forum.php?mod=viewthread&tid=710438&extra=page%3D1%26filter%3Dauthor%26orderby%3Ddateline"
    },
    {
      "name":"大佬们最近有没有度盘续费车？",
      "url":"https://www.hostloc.com/forum.php?mod=viewthread&tid=710437&extra=page%3D1%26filter%3Dauthor%26orderby%3Ddateline"
    },
    {
      "name":"【大瓜】腾讯真的被老千妈骗了。",
      "url":"https://www.hostloc.com/forum.php?mod=viewthread&tid=710436&extra=page%3D1%26filter%3Dauthor%26orderby%3Ddateline"
    },
    {
      "name":"请问aws解锁奈飞的么",
      "url":"https://www.hostloc.com/forum.php?mod=viewthread&tid=710435&extra=page%3D1%26filter%3Dauthor%26orderby%3Ddateline"
    },
    {
      "name":"gandi的码子还有人要？",
      "url":"https://www.hostloc.com/forum.php?mod=viewthread&tid=710434&extra=page%3D1%26filter%3Dauthor%26orderby%3Ddateline"
    },
    {
      "name":"30+剩余价值收ikoula4.5o",
      "url":"https://www.hostloc.com/forum.php?mod=viewthread&tid=710433&extra=page%3D1%26filter%3Dauthor%26orderby%3Ddateline"
    },
    {
      "name":"结",
      "url":"https://www.hostloc.com/forum.php?mod=viewthread&tid=710432&extra=page%3D1%26filter%3Dauthor%26orderby%3Ddateline"
    }
  ]
}