{
  "time":"2020-06-29 06:59:50",
  "title":"澎湃新闻",
  "data":[
    {
      "name":"人民日报海外版：美国涉港法案，废纸一张！",
      "url":"https://www.thepaper.cn/newsDetail_forward_8032277"
    },
    {
      "name":"美国新冠肺炎确诊病例超253.9万例，死亡逾12.5万例",
      "url":"https://www.thepaper.cn/newsDetail_forward_8031875"
    },
    {
      "name":"美国疾控中心前主任：确诊病例数据可能在“数周内继续恶化”",
      "url":"https://www.thepaper.cn/newsDetail_forward_8031476"
    },
    {
      "name":"普京：新冠病毒“人工来源”的说法没有根据",
      "url":"https://www.thepaper.cn/newsDetail_forward_8028246"
    },
    {
      "name":"南非新增新冠肺炎确诊病例6334例，累计138134例",
      "url":"https://www.thepaper.cn/newsDetail_forward_8031587"
    },
    {
      "name":"埃及新增新冠肺炎确诊病例1265例，累计65188例",
      "url":"https://www.thepaper.cn/newsDetail_forward_8031546"
    },
    {
      "name":"美国卫生部长警告：美国控制疫情的窗口正在关闭",
      "url":"https://www.thepaper.cn/newsDetail_forward_8031442"
    },
    {
      "name":"土耳其新增新冠肺炎确诊病例1356例，累计197239例",
      "url":"https://www.thepaper.cn/newsDetail_forward_8031376"
    },
    {
      "name":"出口民调显示波兰现任总统杜达在总统大选首轮中获胜",
      "url":"https://www.thepaper.cn/newsDetail_forward_8031325"
    },
    {
      "name":"约翰斯·霍普金斯大学：全球新冠累计死亡病例超50万例",
      "url":"https://www.thepaper.cn/newsDetail_forward_8031250"
    },
    {
      "name":"巴基斯坦新增新冠确诊病例4072例，累计205532例",
      "url":"https://www.thepaper.cn/newsDetail_forward_8028447"
    },
    {
      "name":"新冠肺炎确诊病例激增，特朗普团队推迟两州竞选活动",
      "url":"https://www.thepaper.cn/newsDetail_forward_8028242"
    },
    {
      "name":"福州一厂房突发大火，70余名消防员紧急救援",
      "url":"https://www.thepaper.cn/newsDetail_forward_8028240"
    },
    {
      "name":"北京海淀区玉泉东市场周边10个社区解除封闭管控",
      "url":"https://www.thepaper.cn/newsDetail_forward_8028230"
    },
    {
      "name":"爱沙尼亚环境保护局在空气中检测到少量核粒子",
      "url":"https://www.thepaper.cn/newsDetail_forward_8028229"
    },
    {
      "name":"伊拉克新增新冠肺炎确诊病例2140例，累计45402例",
      "url":"https://www.thepaper.cn/newsDetail_forward_8028228"
    },
    {
      "name":"香港社会各界通过形式多样的活动庆回归迎立法",
      "url":"https://www.thepaper.cn/newsDetail_forward_8028227"
    },
    {
      "name":"新疆和田遭遇强沙尘天气，最小能见度不足50米",
      "url":"https://www.thepaper.cn/newsDetail_forward_8028224"
    },
    {
      "name":"C919飞机开启高温专项试飞，成功降落新疆吐鲁番交河机场",
      "url":"https://www.thepaper.cn/newsDetail_forward_8028222"
    },
    {
      "name":"四川冕宁特大暴雨灾害已致12人遇难、10人失联",
      "url":"https://www.thepaper.cn/newsDetail_forward_8028218"
    }
  ]
}