{
  "time":"2020-06-19 04:29:28",
  "title":"头条2",
  "data":[
    {
      "name":"习近平对全军战略管理集训作出重要指示",
      "url":"https://www.toutiao.com/group/6839698695034765836/"
    },
    {
      "name":"习近平向“一带一路”国际合作高级别视频会议发表书面致辞",
      "url":"https://www.toutiao.com/group/6839681012482441742/"
    },
    {
      "name":"不拘一格推精品“出彩河南”社会主义核心价值观主题微电影（微视频）推新工程启动",
      "url":"https://www.toutiao.com/group/6839618140981166599/"
    },
    {
      "name":"杨陌题《涅槃·北京“动批”30年》书名",
      "url":"https://www.toutiao.com/group/6839642460914713088/"
    },
    {
      "name":"在孩子面前，家长不要做哪些事情？",
      "url":"https://www.toutiao.com/group/6839449815844716800/"
    },
    {
      "name":"今年快40了，晒晒你们都有多少存款，怎么样？",
      "url":"https://www.toutiao.com/group/6836209565692854536/"
    }
  ]
}