{
  "time":"2020-06-13 04:15:44",
  "title":"头条4",
  "data":[
    {
      "name":"习近平就布隆迪总统恩库伦齐扎逝世向布隆迪当选总统恩达伊施米耶致唁电",
      "url":"https://www.toutiao.com/group/6837405377173127688/"
    },
    {
      "name":"两次通话 习主席再谈这个全球抗疫根本大计",
      "url":"https://www.toutiao.com/group/6837350356989510152/"
    },
    {
      "name":"减脂期，鱼油、CLA、左旋肉碱的重要性排名怎么样？",
      "url":"https://www.toutiao.com/group/6837497766923829518/"
    },
    {
      "name":"才刚宣布涨价，沙特又下调亚洲石油客户供应！对中国有何影响？",
      "url":"https://www.toutiao.com/group/6837483667405668876/"
    },
    {
      "name":"自己家孩子老跟一个欺负他的孩子一起玩，怎么办？",
      "url":"https://www.toutiao.com/group/6837256043026710787/"
    },
    {
      "name":"为什么我们可以听到别人的脚步声，却听不到我们自己的脚步声？",
      "url":"https://www.toutiao.com/group/6836707782184403469/"
    }
  ]
}