{
  "time":"2020-07-09 18:53:02",
  "title":"头条2",
  "data":[
    {
      "name":"图解：“数读”习近平2020上半年重点工作部署",
      "url":"https://www.toutiao.com/group/6846918379043815950/"
    },
    {
      "name":"勇担时代使命 重温习近平对青年人的殷殷寄语",
      "url":"https://www.toutiao.com/group/6847100697410961927/"
    },
    {
      "name":"2020-07-09 南阳镇平天气多云,今日最高气温 32 ℃，最低气温 23 ℃，风向风速：微风,降雨概率：33%防晒指数今天外出最好涂擦SPF大于15，PA+的护肤品，以免晒伤。心情指数天气炎热，比较晒，容易使人比较烦躁，心情指数较差，要注意及时调整情绪。美发指数今天的天气有点晒，",
      "url":"https://www.toutiao.com/group/1671702208680972/"
    },
    {
      "name":"说起山东，印象最深刻的还是在抖音上山东人集体去长辈家里拜年的场景，说实话，被震撼到了！山东拜年的习俗是对中国古代“跪拜礼”最好的诠释了。也说明了中国儒家学派创始人孔子的思想，对山东影响很深，这是一个注重礼仪的城市。随着科技的发展，山东也即将迎来了新的曙光。近日，山东省淄博市与阿里巴巴合作战略升级",
      "url":"https://www.toutiao.com/group/1671728017591299/"
    },
    {
      "name":"如何反驳“中国应全面去工业化”的观点？",
      "url":"https://www.toutiao.com/group/6847406917061804301/"
    }
  ]
}