{
  "time":"2020-05-26 13:51:50",
  "title":"头条3",
  "data":[
    {
      "name":"荆楚东风起 浴火正重生——习近平参加湖北代表团审议纪实",
      "url":"https://www.toutiao.com/group/6831005626961756683/"
    },
    {
      "name":"小小的口罩，大大的中国",
      "url":"https://www.toutiao.com/group/6830697176276926984/"
    },
    {
      "name":"吴谦：搞“台独”就是死路一条，搞武力对抗就是自取灭亡",
      "url":"https://www.toutiao.com/group/1667279947274302/"
    },
    {
      "name":"有没有我的世界一改创造就死的指令？",
      "url":"https://www.toutiao.com/group/6830612087106961675/"
    },
    {
      "name":"故事：心上人对我呵护备至，我做好嫁他准备，他却当我面求婚他人",
      "url":"https://www.toutiao.com/group/6811748007768228356/"
    },
    {
      "name":"为避免“丧偶式育儿”，请在月子期间用好你家男人，这些事交给他",
      "url":"https://www.toutiao.com/group/6829664996746592771/"
    },
    {
      "name":"儿子受伤，为了帮助他恢复，爸爸亲手开发了便携诊断仪器",
      "url":"https://www.toutiao.com/group/6830977007304573448/"
    },
    {
      "name":"有了肾结石还能吃豆腐吗？营养专家：不但能吃，还鼓励吃豆腐",
      "url":"https://www.toutiao.com/group/6791785863077429764/"
    },
    {
      "name":"面试想拿13K，HR说：“你只值8K”，该怎么回答？",
      "url":"https://www.toutiao.com/group/6674229636651548941/"
    },
    {
      "name":"不学习能考上省考么？",
      "url":"https://www.toutiao.com/group/6830732175323693325/"
    }
  ]
}