{
  "time":"2020-06-29 22:58:33",
  "title":"头条8",
  "data":[
    {
      "name":"中共中央政治局召开会议 审议《中国共产党军队党的建设条例》和《中国共产党基层组织选举工作条例》习近平主持会议",
      "url":"https://www.toutiao.com/group/6843690875072021005/"
    },
    {
      "name":"「央视快评」切实把确保人民生命安全放在第一位落到实处",
      "url":"https://www.toutiao.com/group/6843636383718834696/"
    },
    {
      "name":"从抖音春招谈起：直播场景的价值转换",
      "url":"https://www.toutiao.com/group/6843614081648165389/"
    },
    {
      "name":"《天龙八部》中扫地僧为什么可以秒杀萧远山和慕容博？",
      "url":"https://www.toutiao.com/group/6637764923071922436/"
    },
    {
      "name":"《西游记》中天蓬元帅被玉帝贬下凡间成了猪八戒，调戏嫦娥的后果真的这么严重吗？",
      "url":"https://www.toutiao.com/group/6733077149168697603/"
    }
  ]
}