{
  "time":"2020-07-03 15:37:19",
  "title":"头条9",
  "data":[
    {
      "name":"今年三次深改委会议，中央强调了这些卫生领域重点",
      "url":"https://www.toutiao.com/group/6845107770216153613/"
    },
    {
      "name":"「每日一习话」确保基层治理正确方向",
      "url":"https://www.toutiao.com/group/6845030711934583303/"
    },
    {
      "name":"变革管理，恒变者安！看恒安保持高效率持续创新之道",
      "url":"https://www.toutiao.com/group/6845128572718285323/"
    },
    {
      "name":"你喜欢《武林外传》的原因是什么？",
      "url":"https://www.toutiao.com/group/6844838371991437571/"
    },
    {
      "name":"西瓜熟了，7月西瓜的季节。记得小时候在农村，每家每户都有种西瓜，我们家也不例外。但是西瓜成熟了之后，有人会去偷，所以，每到西瓜成熟的那段时期，都必须有人在地里面守着。于是七月放了暑假我和我的堂妹每年都会去守西瓜。在西瓜地边打个小木棚子，白天由我和妹妹守，晚上爸爸来接班。其实那个棚子里面夏天是",
      "url":"https://www.toutiao.com/group/1671178652073996/"
    }
  ]
}