{
  "time":"2020-06-29 09:23:23",
  "title":"头条5",
  "data":[
    {
      "name":"时政微周刊丨总书记的一周（6月22日—6月28日）",
      "url":"https://www.toutiao.com/group/6843556460970902027/"
    },
    {
      "name":"习近平旁征博引话“实干”",
      "url":"https://www.toutiao.com/group/6843568587873976840/"
    },
    {
      "name":"我们希望每一个创业者，都成为现实的理想主义者，践行知行合一。这是说，理想是发展的根本，只有不忘初心，才能知行合一；而现实则是推进我们前进的武器，此心不动，在实践中锻炼，在困难中所得，才能做到知行合一。创业的本质并不仅仅是对财富和生命的追求，更多的是在实现自我价值过程中，对心力、心智、心胸的历练，",
      "url":"https://www.toutiao.com/group/1668716264947720/"
    },
    {
      "name":"良药变“毒药”？67岁大爷竟3次喝中药喝进医院，一查原因懵了",
      "url":"https://www.toutiao.com/group/6842191444237615619/"
    },
    {
      "name":"外贸业务员是不是一天都宅在电脑前工作？",
      "url":"https://www.toutiao.com/group/6843530768426500359/"
    },
    {
      "name":"关于负债二三事",
      "url":"https://www.toutiao.com/group/6843202742983328269/"
    },
    {
      "name":"爱心人士建议立法，每年财政拨款用于保护流浪猫狗，你支持吗？",
      "url":"https://www.toutiao.com/group/6843368012864078088/"
    }
  ]
}