{
  "time":"2020-07-04 23:22:38",
  "title":"头条3",
  "data":[
    {
      "name":"上半年三次深改委会议 中央这样谋划全面深改蓝图",
      "url":"https://www.toutiao.com/group/6845613387766825485/"
    },
    {
      "name":"「每日一习话」尽最大努力保护人民生命安全和身体健康",
      "url":"https://www.toutiao.com/group/6845424137909830147/"
    },
    {
      "name":"5G信号“配送员”、兼职保险查勘员……看这些企业的“花式”用工",
      "url":"https://www.toutiao.com/group/6845639308406161927/"
    },
    {
      "name":"连续多天新增破5万，美总统称已控制疫情，成功挽救数百万人生命",
      "url":"https://www.toutiao.com/group/6845576182163833351/"
    },
    {
      "name":"头条经常出现大白话对联，我觉得就是对传统文化的亵渎，你认为呢？",
      "url":"https://www.toutiao.com/group/6845390601468035335/"
    },
    {
      "name":"印度首位女总理：一个月让400万男子绝育，67岁被贴身警卫刺杀",
      "url":"https://www.toutiao.com/group/6845496206206960139/"
    },
    {
      "name":"印度抵制效果显现，售卖我国产品商户陷入危机，中国手机销量下滑",
      "url":"https://www.toutiao.com/group/6845550911532564996/"
    }
  ]
}