{
  "time":"2020-05-09 01:50:32",
  "title":"头条8",
  "data":[
    {
      "name":"中共中央召开党外人士座谈会 习近平主持并发表重要讲话",
      "url":"https://www.toutiao.com/group/6824447685571904014/"
    },
    {
      "name":"习近平同俄罗斯总统普京通电话",
      "url":"https://www.toutiao.com/group/6824489876931478030/"
    },
    {
      "name":"又一款VR音游登陆Oculus Quest",
      "url":"https://www.toutiao.com/group/6824366932196590084/"
    },
    {
      "name":"求助！孩子老吸自己大拇指，有什么办法可以改变这坏习惯吗？",
      "url":"https://www.toutiao.com/group/6824355534326464776/"
    },
    {
      "name":"现在创业做什么比较好，利润可观？",
      "url":"https://www.toutiao.com/group/6824379238242582791/"
    },
    {
      "name":"用炸药包给伪军上上课！八路军主力要打炮楼，短枪队为何连忙阻止",
      "url":"https://www.toutiao.com/group/6824296937127150092/"
    }
  ]
}