{
  "time":"2020-05-15 00:26:39",
  "title":"头条10",
  "data":[
    {
      "name":"中共中央政治局常务委员会召开会议 习近平主持",
      "url":"https://www.toutiao.com/group/6826656676678992397/"
    },
    {
      "name":"热解读 | 山西行首提环保“四治”习近平生态足迹背后有深意",
      "url":"https://www.toutiao.com/group/6826662669332775438/"
    },
    {
      "name":"100个有趣的亲子游戏超全，再也不用担心不知道怎么跟孩子互动了",
      "url":"https://www.toutiao.com/group/6826712959905956359/"
    },
    {
      "name":"“高精尖”燃气泄漏检测小能手今日正式上岗",
      "url":"https://www.toutiao.com/group/6826690655855575556/"
    },
    {
      "name":"泰坦尼克号又称“永不沉没的巨轮”，为何第一次航行就沉没了？",
      "url":"https://www.toutiao.com/group/6826729738531242500/"
    },
    {
      "name":"损失预超300亿！已有7300家影视公司注销，今年电影市场会怎样？",
      "url":"https://www.toutiao.com/group/6826683594455384589/"
    },
    {
      "name":"肉松不用买了，不用面包机，1把炒锅在家就能做，比买的还美味",
      "url":"https://www.toutiao.com/group/6826635817939632654/"
    }
  ]
}