{
  "time":"2020-06-27 18:50:20",
  "title":"头条10",
  "data":[
    {
      "name":"心中最重要的位置",
      "url":"https://www.toutiao.com/group/6842940743472906766/"
    },
    {
      "name":"真正做到为官一任，造福一方",
      "url":"https://www.toutiao.com/group/6842897032844149256/"
    },
    {
      "name":"5月全球黄金ETF净流入154吨 总持仓量创新高",
      "url":"https://www.toutiao.com/group/6842954707393053191/"
    },
    {
      "name":"曾经以为最大的敌人是对手，后来以为最大的敌人是自己现在明白，最大的敌人其实是时间！",
      "url":"https://www.toutiao.com/group/1670626322991115/"
    },
    {
      "name":"有没有很“狂”很霸气的诗句？",
      "url":"https://www.toutiao.com/group/6842952907106042116/"
    },
    {
      "name":"农村学校男教师越来越少，近5年来我校未入职一位男教师，怎么解决？",
      "url":"https://www.toutiao.com/group/6842922510116389134/"
    },
    {
      "name":"蚊帐空调适合孕妇睡吗？会不会缺痒？",
      "url":"https://www.toutiao.com/group/6842783409585897743/"
    },
    {
      "name":"2005年象山茶厂布朗山野生茶，象山茶厂创始人是现任厂长周俊宇的父亲周建华，他从上世纪80年代开始潜心研究茶，并进入了普洱茶行业里面的“黄埔军校”——勐海茶厂。他是从勐海茶厂走出的众多茶人之一，并一直致力于改良和创新制茶工艺，最后总结出一套崭新的制茶技术。2002年，勐海茶厂进行了一场大的改革，许多",
      "url":"https://www.toutiao.com/group/1670635217232910/"
    }
  ]
}