{
  "time":"2020-06-18 20:11:18",
  "title":"头条1",
  "data":[
    {
      "name":"第一报道 | 习主席提出的四个“坚定不移”，让世界感受到中国情谊、中国担当",
      "url":"https://www.toutiao.com/group/6839539632313467406/"
    },
    {
      "name":"中非团结抗疫，这些承诺习近平再次强调",
      "url":"https://www.toutiao.com/group/6839608828556739080/"
    },
    {
      "name":"#心晴计划# 大家遇到烦心的事是怎么排除的？有人会逛街购物，有人会出门旅游，有人会大吃大喝，也有人会昏头大睡。我遇到烦心事解决的方式别具一格，那就是看言情小说。我也不知道为什么，遇到烦心事郁结的心头难以抒怀，不想跟别人倾诉，更不想让人知道，每当这时我会找一部喜欢的言情小说，安静的去读",
      "url":"https://www.toutiao.com/group/1669831435005967/"
    },
    {
      "name":"【293期】检察长列席审委会 实现“以审判为中心”效果最优化",
      "url":"https://www.toutiao.com/group/6839607269064180228/"
    },
    {
      "name":"以低价车为诱饵诈骗近十万元",
      "url":"https://www.toutiao.com/group/6839588759156032008/"
    },
    {
      "name":"联盟协调 各方助力丨多部委关注“铜娃娃”治疗用药供应保障",
      "url":"https://www.toutiao.com/group/6839490187429413389/"
    },
    {
      "name":"印度靠“金色牛奶”抵御新冠病毒靠谱吗？",
      "url":"https://www.toutiao.com/group/6839345628863005197/"
    },
    {
      "name":"抗疫女护士讨要说法!“抗疫时无防护措施冲锋在一线，安全后却被辞退”医院做法合适吗？",
      "url":"https://www.toutiao.com/group/6839619393556513039/"
    }
  ]
}