{
  "time":"2020-06-20 13:26:54",
  "title":"头条9",
  "data":[
    {
      "name":"团结抗疫 习近平这样推动构建中非命运共同体",
      "url":"https://www.toutiao.com/group/6840234436458447373/"
    },
    {
      "name":"「央视快评」加强“一带一路”国际合作 携手抗击新冠肺炎疫情",
      "url":"https://www.toutiao.com/group/6840280924848914951/"
    },
    {
      "name":"✨很爱的kiko的产品✨真的觉得是平价系列里面的战斗机✨新推出的指甲油当然不能错过💅40 浓郁的栗子色 很适合秋冬 💅53温柔玫瑰色 肉肉粉粉的感觉 很显白 很温柔两个颜色搭配一起也很好看呀～#指甲油#",
      "url":"https://www.toutiao.com/group/1669919057112075/"
    },
    {
      "name":"如果选择去旅游，你最先想到的是哪里？是伟人故里还是安静的地方？",
      "url":"https://www.toutiao.com/group/6840227368239317262/"
    }
  ]
}