{
  "time":"2020-06-06 20:15:30",
  "title":"头条7",
  "data":[
    {
      "name":"第一报道 | 周五晚上，习主席两次通话传递这些重要信息",
      "url":"https://www.toutiao.com/group/6835076055103963662/"
    },
    {
      "name":"「央视快评」推动中西医药相互补充协调发展",
      "url":"https://www.toutiao.com/group/6834790583286891020/"
    },
    {
      "name":"正副领导推诿扯皮，我该怎么办？三步教你看清职场矛盾冲突问题",
      "url":"https://www.toutiao.com/group/6835134118758449667/"
    },
    {
      "name":"一组乡村教师的国画",
      "url":"https://www.toutiao.com/group/6835162037312553480/"
    }
  ]
}