{
  "time":"2020-05-17 11:48:10",
  "title":"头条8",
  "data":[
    {
      "name":"时政微纪录丨最是深情暖人心",
      "url":"https://www.toutiao.com/group/6827605758444569091/"
    },
    {
      "name":"「央视快评」没有任何力量能够阻挡中国人民实现梦想",
      "url":"https://www.toutiao.com/group/6827603755551162892/"
    },
    {
      "name":"iPhone 12售价曝光，定价低至4200元？或用上120Hz屏",
      "url":"https://www.toutiao.com/group/6827279344289710600/"
    },
    {
      "name":"毛戈平给网红张大奕化妆，看完前后对比，网友：丝毫不输总裁夫人",
      "url":"https://www.toutiao.com/group/6818451331640984071/"
    }
  ]
}