{
  "time":"2020-06-18 13:10:37",
  "title":"头条2",
  "data":[
    {
      "name":"时政新闻眼丨中非特别峰会，习近平提出这些中国主张",
      "url":"https://www.toutiao.com/group/6839471706403242510/"
    },
    {
      "name":"陈晓东谈中非团结抗疫特别峰会成果",
      "url":"https://www.toutiao.com/group/6839366990621049351/"
    },
    {
      "name":"#英国美食#有比炸鱼薯条更能代表英国特色的食物吗？显然没有！把鳕鱼(Cod)包上面粉，下油锅小火炸熟， 加上薯条， 再配上蛋黄酱(Mayonnaise) 或者番茄酱(Ketchup). 这就是从狄更斯的雾都孤儿里就存在的英国特色食物炸鱼薯条。想象一下在伦敦的凄风冷雨中，来一套热乎乎香喷喷的炸鱼薯条是",
      "url":"https://www.toutiao.com/group/1669657447458830/"
    },
    {
      "name":"北京做IT年薪35万，考上浙江省直机关公务员，但被分到温州工作，要不要去温州呢？",
      "url":"https://www.toutiao.com/group/6839272084159103247/"
    },
    {
      "name":"糖尿病合并乙肝饮食，患者朋友请注意查收1、可以多吃一些豆类的食物，可以补充优质蛋白2、可以多吃粗、杂粮，对降低血糖、血脂有帮助3、多吃新鲜蔬菜4、糖尿病不能多吃盐、糖糖尿病合并乙肝，肾炎的几率提高，如果糖尿病没有得到好的控制，可能会出现糖尿病相关的肾炎。@健康中国 @头条健康",
      "url":"https://www.toutiao.com/group/1669807422522380/"
    },
    {
      "name":"告诉大家一些手机的秘密！苹果不会像小米一样发烫！小米信号要比华为强多了！华为音质要比vivo舒服多了！vivo拍照要荣耀清晰多了！荣耀充电比oppo快多了！oppo颜值比苹果高多了！",
      "url":"https://www.toutiao.com/group/1669766707094528/"
    },
    {
      "name":"摆摊了吗？疫情常态下，知识产权服务行业该何去何从",
      "url":"https://www.toutiao.com/group/6839208311535960588/"
    }
  ]
}