{
  "time":"2020-06-04 19:46:39",
  "title":"头条5",
  "data":[
    {
      "name":"第一报道 | 同德国总理通电话，习主席谈到这三件大事",
      "url":"https://www.toutiao.com/group/6834325837647446541/"
    },
    {
      "name":"人民日报：构建起强大的公共卫生体系",
      "url":"https://www.toutiao.com/group/6834390347628413453/"
    },
    {
      "name":"工行成立“工银大学新星学院”打造校园联盟生态新模式",
      "url":"https://www.toutiao.com/group/6834314097836687886/"
    },
    {
      "name":"华侨权益保护条例已纳入北京市人大常委会今年立项论证项目",
      "url":"https://www.toutiao.com/group/6834380594906923534/"
    },
    {
      "name":"广汽本田、东风本田召回国产汽车 超77万辆",
      "url":"https://www.toutiao.com/group/6834321510149128711/"
    },
    {
      "name":"江西乐安：“保险+救助”“特邀法官”机制推动“切实解决执行难”",
      "url":"https://www.toutiao.com/group/6834453581760823816/"
    },
    {
      "name":"第四届安徽怀宁国际蓝莓文化旅游节来沪推介",
      "url":"https://www.toutiao.com/group/6834132591486960142/"
    },
    {
      "name":"在更高起点层次目标上推进经济体制改革",
      "url":"https://www.toutiao.com/group/6834303529629254152/"
    },
    {
      "name":"巴基斯坦总统会见中国人民解放军抗疫医疗专家组",
      "url":"https://www.toutiao.com/group/6834148701020094989/"
    },
    {
      "name":"最新球员身价榜：姆巴佩居首 梅西第九",
      "url":"https://www.toutiao.com/group/6834290169206538759/"
    }
  ]
}