{
  "time":"2020-06-06 13:19:27",
  "title":"头条9",
  "data":[
    {
      "name":"第一报道 | 习近平的“两山论”，让世界读懂“美丽中国”",
      "url":"https://www.toutiao.com/group/6834871370115973646/"
    },
    {
      "name":"「每日一习话」文明其精神 野蛮其体魄",
      "url":"https://www.toutiao.com/group/6835083166512841223/"
    },
    {
      "name":"智能时代要照顾那些“掉队”的人",
      "url":"https://www.toutiao.com/group/6834789854862115335/"
    },
    {
      "name":"装修时免漆板和油漆板木工加工费一样吗？",
      "url":"https://www.toutiao.com/group/6834727813531042063/"
    },
    {
      "name":"办公室常见腰疼问题！是你的髂腰肌出问题！如何康复训练改善？",
      "url":"https://www.toutiao.com/group/6834693337040028174/"
    },
    {
      "name":"广本VE-1卖多少钱？值不值？",
      "url":"https://www.toutiao.com/group/6807007881385214222/"
    },
    {
      "name":"2020夏日流行色，太美了",
      "url":"https://www.toutiao.com/group/6833986608027402759/"
    },
    {
      "name":"李白和苏轼为什么没有能力拯救唐宋的没落？",
      "url":"https://www.toutiao.com/group/6832089123671507464/"
    }
  ]
}