{
  "time":"2020-05-18 22:20:59",
  "title":"头条1",
  "data":[
    {
      "name":"独家视频丨习近平在第73届世界卫生大会视频会议开幕式上致辞",
      "url":"https://www.toutiao.com/group/6828157494364209676/"
    },
    {
      "name":"回顾七年两会，习近平的十个精彩妙喻",
      "url":"https://www.toutiao.com/group/6828063842698789380/"
    },
    {
      "name":"澳大利亚用新办法对付中国：施压世卫调查疫情真相，获得62国支持",
      "url":"https://www.toutiao.com/group/6828121851277869579/"
    },
    {
      "name":"女人不到50，下半身就出现四种迹象，提示你已经早衰了，很难长寿",
      "url":"https://www.toutiao.com/group/6828073921066041868/"
    },
    {
      "name":"紧急扩散！湖北大学生上海求职确诊！活动轨迹查清，动车车次、入住宾馆公布",
      "url":"https://www.toutiao.com/group/6828143685910135304/"
    },
    {
      "name":"习近平宣布：捐20亿美元抗疫",
      "url":"https://www.toutiao.com/group/6828153630168711692/"
    },
    {
      "name":"北京打工：21平出租屋两张床，住婆媳老公孩子五口人，图什么？",
      "url":"https://www.toutiao.com/group/6823826751118901763/"
    },
    {
      "name":"\"小婉君\"嫁豪门被王祖贤插足，婆婆撑腰：就当儿子2000万叫了只鸡",
      "url":"https://www.toutiao.com/group/6828109978683834883/"
    },
    {
      "name":"「号外！号外！」官网通知：2020年7月份的日语能力考试宣布取消",
      "url":"https://www.toutiao.com/group/6828099316150698500/"
    },
    {
      "name":"北京户口五年摇不上汽车号牌，该怎么办？",
      "url":"https://www.toutiao.com/group/6770273666186871047/"
    }
  ]
}