{
  "time":"2020-06-13 08:07:43",
  "title":"头条9",
  "data":[
    {
      "name":"习近平就布隆迪总统恩库伦齐扎逝世向布隆迪当选总统恩达伊施米耶致唁电",
      "url":"https://www.toutiao.com/group/6837405377173127688/"
    },
    {
      "name":"两次通话 习主席再谈这个全球抗疫根本大计",
      "url":"https://www.toutiao.com/group/6837350356989510152/"
    },
    {
      "name":"减肥药内含国家一类管制精神药品入境，难逃海关“火眼金睛”",
      "url":"https://www.toutiao.com/group/6837473609905078788/"
    },
    {
      "name":"6月考驾照又变难了，驾校要求提高，没考驾照的要受苦了",
      "url":"https://www.toutiao.com/group/6836146543238578692/"
    }
  ]
}