{
  "time":"2020-06-27 23:07:05",
  "title":"头条5",
  "data":[
    {
      "name":"这四个字，道出习近平的为民情怀",
      "url":"https://www.toutiao.com/group/6843025174577545731/"
    },
    {
      "name":"「在习近平新时代中国特色社会主义思想指引下——育新机 开新局」骨干企业创新引领 稳定提升产业链",
      "url":"https://www.toutiao.com/group/6843025630531944972/"
    },
    {
      "name":"时间过的真快，过了端午就快放暑假了。孩子明天期未考试，老师在群里提示大家要好好复习备考，还说了句至励名言“临阵磨枪，不快也光”，我说给儿子听，他还不明白是啥意思，问我枪为什么要磨呢？好吧~只能在给他科普一下什么叫红樱枪了......说完了红樱枪的前世今生，最后我告诉儿子，你爹我给不了你乾坤圈和风火",
      "url":"https://www.toutiao.com/group/1670654002536452/"
    },
    {
      "name":"崔智友为什么不介意丈夫曾是牛郎？",
      "url":"https://www.toutiao.com/group/6832640297353085184/"
    },
    {
      "name":"打败美国注定天方夜谭？为何说军事强大的俄罗斯不可能挑战美国？",
      "url":"https://www.toutiao.com/group/6843025306317209870/"
    },
    {
      "name":"#传奇# 我问管理：为什么3个限时任务新手装只有道士的额外需要3个蜘蛛线？管理：这个任务除了为了帮助新手度过前期之外，还根据三龙卫传说编辑的任务，圣战，法神均陨落在赤月峡谷，晋升天尊，新人要代替天尊去赤月打探一下情报才算完成，另外两个属于陨落后精神力所凝聚的，所以只要三根金条作为祭品就好。（金币很",
      "url":"https://www.toutiao.com/group/1670578618337291/"
    },
    {
      "name":"百度为什么不像Google那样研发操作系统？",
      "url":"https://www.toutiao.com/group/6843036950094414350/"
    },
    {
      "name":"张博“毒瘾”发作家暴谭维维反被打骨折，世界冠军张伟丽一语中的",
      "url":"https://www.toutiao.com/group/6842598265783845384/"
    },
    {
      "name":"体操女神与普京绯闻不断，未婚生下儿子撞脸普京，如今她官运旺盛",
      "url":"https://www.toutiao.com/group/6843005497247793672/"
    }
  ]
}