{
  "time":"2020-05-10 06:23:11",
  "title":"头条7",
  "data":[
    {
      "name":"联播+丨习近平：时刻绷紧疫情防控这根弦 扎实推进复工复产复学",
      "url":"https://www.toutiao.com/group/6824648072945992196/"
    },
    {
      "name":"习近平总书记关切事丨武汉“解封”满月观察",
      "url":"https://www.toutiao.com/group/6824801749786690060/"
    },
    {
      "name":"俗语“凳不离三、门不离五、床不离七”，老祖宗留下来的讲究！",
      "url":"https://www.toutiao.com/group/6822846742510174734/"
    },
    {
      "name":"忆母亲~谨以此诗献给天下母亲~THE SUMMER BREEZE 「3」",
      "url":"https://www.toutiao.com/group/6824701086134174221/"
    },
    {
      "name":"特朗普亲信的身边人接连确诊，特朗普如今怎么样了？",
      "url":"https://www.toutiao.com/group/6824772333308215820/"
    },
    {
      "name":"英语课感觉自己有点跟不上了，是要继续跟老师上课还是自己学习？",
      "url":"https://www.toutiao.com/group/6824770935426384140/"
    }
  ]
}