{
  "time":"2020-06-28 20:31:54",
  "title":"头条6",
  "data":[
    {
      "name":"习近平对防汛救灾工作作出重要指示",
      "url":"https://www.toutiao.com/group/6843367138967683597/"
    },
    {
      "name":"习近平点赞过的那些优秀共产党员",
      "url":"https://www.toutiao.com/group/6843209063338082829/"
    },
    {
      "name":"全国工商联召开“政企面对面：保产业链供应链稳定”座谈会 | 长江电气党委书记、董事长王新城作主题汇报https://mp.weixin.qq.com/s/_3IvO1f5LoTCrnE5ZD1S9Q",
      "url":"https://www.toutiao.com/group/1670695230364679/"
    },
    {
      "name":"一个人全职在家带孩子，真的没时间做饭做家务吗？",
      "url":"https://www.toutiao.com/group/6843260566430908672/"
    }
  ]
}