{
  "time":"2020-06-16 17:46:02",
  "title":"头条9",
  "data":[
    {
      "name":"联播+| 习近平民法典“讲义”中的人民情怀",
      "url":"https://www.toutiao.com/group/6838750510044938765/"
    },
    {
      "name":"一图速览：实施好民法典，习近平总书记如何部署重点工作",
      "url":"https://www.toutiao.com/group/6838816012972851720/"
    },
    {
      "name":"30岁以前买保险怎么规划？哪家保险公司最靠谱？",
      "url":"https://www.toutiao.com/group/6838863190454124807/"
    },
    {
      "name":"牛仔裤合不合身，裤裆下面见分晓｜基本款",
      "url":"https://www.toutiao.com/group/6807963643309720076/"
    },
    {
      "name":"巴基斯坦和孟加拉国原是一国，分开之后，两个国家的关系如何？",
      "url":"https://www.toutiao.com/group/6838853021742235919/"
    },
    {
      "name":"七八十年代的缝纫机，现在能值多少人民币？",
      "url":"https://www.toutiao.com/group/6729356371386433803/"
    }
  ]
}