{
  "time":"2020-05-17 09:04:46",
  "title":"头条9",
  "data":[
    {
      "name":"第一观察｜“50+1”通电话，都和这件大事有关",
      "url":"https://www.toutiao.com/group/6827460545944224264/"
    },
    {
      "name":"110天13次中央政治局常委会会议 聚焦这三大议题",
      "url":"https://www.toutiao.com/group/6827077383984513549/"
    },
    {
      "name":"增值税检查调整问题汇总",
      "url":"https://www.toutiao.com/group/6827379418667680271/"
    },
    {
      "name":"大学生就业该何去何从？",
      "url":"https://www.toutiao.com/group/6827447185261461763/"
    },
    {
      "name":"反常积分知识分享",
      "url":"https://www.toutiao.com/group/6827403870243652110/"
    }
  ]
}