{
  "time":"2020-05-16 06:02:50",
  "title":"知乎全站热榜",
  "data":[
    {
      "name":"如何看待美国疑似彻底封杀华为，公司只要用美国设备造芯片卖华为就要被限制？",
      "url":"https://www.zhihu.com/question/395075061"
    },
    {
      "name":"如何评价2020软科中国大学排名？",
      "url":"https://www.zhihu.com/question/394911925"
    },
    {
      "name":"有哪些发明本意是造福人类最后却给人类太多伤害？发明者有后悔过吗？",
      "url":"https://www.zhihu.com/question/335879505"
    },
    {
      "name":"为什么唯独是美国疫情增长速度这么快？",
      "url":"https://www.zhihu.com/question/385173085"
    },
    {
      "name":"如何评价郑爽的芭蕾舞？",
      "url":"https://www.zhihu.com/question/394538309"
    },
    {
      "name":"如何评价关晓彤的蔬菜三明治？",
      "url":"https://www.zhihu.com/question/393913360"
    },
    {
      "name":"研三了，延毕了。当了一辈子的乖乖女，终于还是闹出了笑话。你不知道我每天活在怎样的地狱里，怎样才能解脱？",
      "url":"https://www.zhihu.com/question/59767069"
    },
    {
      "name":"520 送女朋友什么礼物合适？",
      "url":"https://www.zhihu.com/question/393509843"
    },
    {
      "name":"如何评价《王者荣耀》5月15号公告的法术装备调整，会带来哪些影响？",
      "url":"https://www.zhihu.com/question/394993893"
    },
    {
      "name":"如何看待台积电宣布将投资 120 亿美元赴美建 5nm 芯片工厂？",
      "url":"https://www.zhihu.com/question/394943394"
    },
    {
      "name":"读博的男朋友和我借钱，你怎么看？",
      "url":"https://www.zhihu.com/question/394038527"
    },
    {
      "name":"如何看待 2020 年中国移动停薪留职鼓励员工创业？",
      "url":"https://www.zhihu.com/question/394817654"
    },
    {
      "name":"男生用什么头像比较吸引女生？",
      "url":"https://www.zhihu.com/question/361207974"
    },
    {
      "name":"我是一名6岁男孩的妈妈，今天孩子玩儿水枪，不小心喷到了别的孩子身上，那个妈妈就不高兴了，我该怎么办？",
      "url":"https://www.zhihu.com/question/394203363"
    },
    {
      "name":"如何看待刘雨昕超话里高材生粉丝卖艺为刘雨昕加油？",
      "url":"https://www.zhihu.com/question/394566566"
    },
    {
      "name":"你最喜欢的微信背景图是什么？",
      "url":"https://www.zhihu.com/question/387738646"
    },
    {
      "name":"如何看待 5 月 15 日丰巢道歉并更新的「关于用户服务调整的说明」？这些调整措施可以接受吗？",
      "url":"https://www.zhihu.com/question/395078506"
    },
    {
      "name":"如何看待本周Epic免费赠送GTA5?",
      "url":"https://www.zhihu.com/question/394728860"
    },
    {
      "name":"《王者荣耀》有哪些意想不到但很强的英雄出装？",
      "url":"https://www.zhihu.com/question/386518734"
    },
    {
      "name":"如何评论湖北宜昌一医生携子跳楼身亡，报告称系家庭矛盾，是否是对死者妻子的二次伤害?",
      "url":"https://www.zhihu.com/question/394559386"
    },
    {
      "name":"如何看待肖战全球后援会就粉丝争议发公告，表示道歉并将整改？",
      "url":"https://www.zhihu.com/question/395079186"
    },
    {
      "name":"如何看待刘雨昕跳popping被超模AA点赞？",
      "url":"https://www.zhihu.com/question/394924044"
    },
    {
      "name":"男生和女生长期打王者会产生感觉吗？",
      "url":"https://www.zhihu.com/question/381907583"
    },
    {
      "name":"疫情当下你敢裸辞吗？",
      "url":"https://www.zhihu.com/question/393375587"
    },
    {
      "name":"如何看待欧美儿童身上出现罕见病，纽约达85人，其他国家达百人，是新冠出现变异了么？",
      "url":"https://www.zhihu.com/question/391270797"
    },
    {
      "name":"朱元璋对待官员这么严厉，甚至苛刻，为什么没有帝逼官反呢？",
      "url":"https://www.zhihu.com/question/392938689"
    },
    {
      "name":"随着曲目越来越多，是否有一天人类会最终处于旋律创无可创，所有旋律都有重复的境地？",
      "url":"https://www.zhihu.com/question/393305051"
    },
    {
      "name":"给汽车加98号油是一种什么样的感觉？",
      "url":"https://www.zhihu.com/question/393672159"
    },
    {
      "name":"内行人怎么看待下颌角手术？",
      "url":"https://www.zhihu.com/question/305195629"
    },
    {
      "name":"高三真的要学到凌晨两三点吗？",
      "url":"https://www.zhihu.com/question/380677229"
    },
    {
      "name":"你们试过最牛逼的减肥方法是什么 ?",
      "url":"https://www.zhihu.com/question/357332126"
    },
    {
      "name":"如何看待 2020 年前 4 月螺蛳粉出口量暴涨？外国人能吃习惯这个口味吗？",
      "url":"https://www.zhihu.com/question/394899124"
    },
    {
      "name":"如何看待因为笔记本屏幕是龙腾而退货的消费者?",
      "url":"https://www.zhihu.com/question/394904211"
    },
    {
      "name":"小学阶段是该让孩子多刷题还是多阅读?",
      "url":"https://www.zhihu.com/question/387030054"
    },
    {
      "name":"如何评价安崎的舞蹈水平?",
      "url":"https://www.zhihu.com/question/379660819"
    },
    {
      "name":"能不能以长远的角度来分析，如果青春有你2刘雨昕C位出道，这个团今后的发展如何？",
      "url":"https://www.zhihu.com/question/392718478"
    },
    {
      "name":"如何评价“连锁餐厅成功毁掉了中国地方菜”的观点？",
      "url":"https://www.zhihu.com/question/395001026"
    },
    {
      "name":"陕西存在感最低（最不出名）的城市是哪个？",
      "url":"https://www.zhihu.com/question/386670899"
    },
    {
      "name":"2020 年，有哪些 15W 落地的 SUV 值得推荐？",
      "url":"https://www.zhihu.com/question/366547673"
    },
    {
      "name":"淘宝卖家可以坏到什么程度？",
      "url":"https://www.zhihu.com/question/367986116"
    },
    {
      "name":"为何单个电子通过双缝会发生干涉？",
      "url":"https://www.zhihu.com/question/61933450"
    },
    {
      "name":"第一次当伴娘有什么地方需要注意呢?",
      "url":"https://www.zhihu.com/question/391735709"
    },
    {
      "name":"第一次买螺蛳粉哪个牌子的好吃？",
      "url":"https://www.zhihu.com/question/374452877"
    },
    {
      "name":"火影忍者里有哪些神一样的设定?或者比较有意思的脑洞?",
      "url":"https://www.zhihu.com/question/41316022"
    },
    {
      "name":"丰臣秀吉非得打朝鲜吗，为什么不能休养生息发展自己的领地呢？",
      "url":"https://www.zhihu.com/question/394143733"
    },
    {
      "name":"防晒伞有必要买贵的么？",
      "url":"https://www.zhihu.com/question/280238194"
    },
    {
      "name":"如何看待薇娅联手联合国助力非洲卢旺达的公益直播？",
      "url":"https://www.zhihu.com/question/395033159"
    },
    {
      "name":"按照现在长辈的育儿理论，以前的孩子是怎么活下来的？",
      "url":"https://www.zhihu.com/question/381176887"
    },
    {
      "name":"如何看待小米卢伟冰突然关注荣耀老熊？",
      "url":"https://www.zhihu.com/question/394561816"
    },
    {
      "name":"宅家仨月变胖20斤，现在国内疫情基本结束，大家会“报复性运动”吗？",
      "url":"https://www.zhihu.com/question/394795635"
    }
  ]
}